main.py
zse-1.4.0.dist-info/METADATA
zse-1.4.0.dist-info/WHEEL
zse-1.4.0.dist-info/entry_points.txt
zse-1.4.0.dist-info/top_level.txt
zse-1.4.0.dist-info/RECORD
