Metadata-Version: 2.4
Name: zse
Version: 1.4.0
Summary: A CLI tool that allows UNSW students to submit work to CSE machines.
Author: Kareem Agha
Classifier: Programming Language :: Python :: 3
Classifier: License :: OSI Approved :: MIT License
Classifier: Operating System :: OS Independent
Requires-Python: >=3.0
Requires-Dist: paramiko
Requires-Dist: colorama
Requires-Dist: platformdirs
Requires-Dist: setuptools
Dynamic: author
Dynamic: classifier
Dynamic: description
Dynamic: description-content-type
Dynamic: requires-dist
Dynamic: requires-python
Dynamic: summary
